quantalogic_toolbox_mcp/__init__.py
quantalogic_toolbox_mcp/tools.py
quantalogic_toolbox_mcp-0.13.0.dist-info/LICENSE
quantalogic_toolbox_mcp-0.13.0.dist-info/METADATA
quantalogic_toolbox_mcp-0.13.0.dist-info/WHEEL
quantalogic_toolbox_mcp-0.13.0.dist-info/entry_points.txt
quantalogic_toolbox_mcp-0.13.0.dist-info/RECORD
