Metadata-Version: 2.3
Name: quantalogic_toolbox_mcp
Version: 0.13.0
Summary: A custom MCP Client for Quantalogic
License: MIT
Keywords: MCP,Quantalogic,toolbox,client
Author: Raphael Mansuy
Author-email: raphael.mansuy@quantalogic.com
Requires-Python: >=3.10
Classifier: Development Status :: 4 - Beta
Classifier: License :: OSI Approved :: MIT License
Classifier: Programming Language :: Python :: 3
Classifier: Programming Language :: Python :: 3.10
Classifier: Programming Language :: Python :: 3.11
Classifier: Programming Language :: Python :: 3.12
Classifier: Programming Language :: Python :: 3.13
Requires-Dist: mcp (>=1.6.0,<2.0.0)
Project-URL: Documentation, https://github.com/quantalogic/toolboxes/tree/main/quantalogic-toolbox-mcp#readme
Project-URL: Homepage, https://github.com/quantalogic/toolboxes/tree/main/quantalogic-toolbox-mcp
Project-URL: Repository, https://github.com/quantalogic/toolboxes/tree/main/quantalogic-toolbox-mcp
